dvsim/__init__.py
dvsim/logging.py
dvsim/modes.py
dvsim/msg_bucket.py
dvsim/msg_buckets.py
dvsim/regression.py
dvsim/scheduler.py
dvsim/sim_results.py
dvsim/test.py
dvsim/testplan.py
dvsim/testplanner.py
dvsim/cli/__init__.py
dvsim/cli/admin.py
dvsim/cli/run.py
dvsim/examples/testplanner/common_testplan.hjson
dvsim/examples/testplanner/foo_dv_doc.md
dvsim/examples/testplanner/foo_sim_results.hjson
dvsim/examples/testplanner/foo_testplan.hjson
dvsim/flow/__init__.py
dvsim/flow/base.py
dvsim/flow/cdc.py
dvsim/flow/factory.py
dvsim/flow/formal.py
dvsim/flow/hjson.py
dvsim/flow/lint.py
dvsim/flow/one_shot.py
dvsim/flow/rdc.py
dvsim/flow/syn.py
dvsim/job/__init__.py
dvsim/job/data.py
dvsim/job/deploy.py
dvsim/job/time.py
dvsim/launcher/__init__.py
dvsim/launcher/base.py
dvsim/launcher/factory.py
dvsim/launcher/fake.py
dvsim/launcher/local.py
dvsim/launcher/lsf.py
dvsim/launcher/nc.py
dvsim/launcher/slurm.py
dvsim/launcher/sge/__init__.py
dvsim/launcher/sge/engine.py
dvsim/launcher/sge/launcher.py
dvsim/launcher/sge/qsubopts.py
dvsim/linting/__init__.py
dvsim/linting/parser.py
dvsim/report/__init__.py
dvsim/report/data.py
dvsim/sim/__init__.py
dvsim/sim/data.py
dvsim/sim/flow.py
dvsim/sim/report.py
dvsim/sim/tool/__init__.py
dvsim/sim/tool/base.py
dvsim/sim/tool/vcs.py
dvsim/sim/tool/xcelium.py
dvsim/templates/__init__.py
dvsim/templates/render.py
dvsim/templates/reports/__init__.py
dvsim/templates/reports/block_report.html
dvsim/templates/reports/redirect.html
dvsim/templates/reports/summary_report.html
dvsim/templates/reports/wrapper.html
dvsim/templates/static/css/bootstrap.min.css
dvsim/templates/static/css/style.css
dvsim/templates/static/js/bootstrap.bundle.min.js
dvsim/templates/static/js/htmx.min.js
dvsim/tool/__init__.py
dvsim/tool/ascentlint.py
dvsim/tool/meridianrdc.py
dvsim/tool/utils.py
dvsim/tool/verilator.py
dvsim/utils/__init__.py
dvsim/utils/check.py
dvsim/utils/fs.py
dvsim/utils/git.py
dvsim/utils/hjson.py
dvsim/utils/json.py
dvsim-1.7.3.dist-info/METADATA
dvsim-1.7.3.dist-info/WHEEL
dvsim-1.7.3.dist-info/entry_points.txt
dvsim-1.7.3.dist-info/licenses/LICENSE
dvsim-1.7.3.dist-info/RECORD
