Metadata-Version: 2.4
Name: dvsim
Version: 1.7.3
Summary: DV system
Author: lowRISC contributors (OpenTitan project)
License-File: LICENSE
Requires-Python: >=3.10
Requires-Dist: click>=8.1.7
Requires-Dist: enlighten>=1.12.4
Requires-Dist: gitpython>=3.1.45
Requires-Dist: hjson>=3.1.0
Requires-Dist: jinja2>=3.1.6
Requires-Dist: logzero>=1.7.0
Requires-Dist: pydantic>=2.9.2
Requires-Dist: pyyaml>=6.0.2
Requires-Dist: tabulate>=0.9.0
Requires-Dist: toml>=0.10.2
Provides-Extra: ci
Requires-Dist: gitpython; extra == 'ci'
Requires-Dist: pyhamcrest>=2.1.0; extra == 'ci'
Requires-Dist: pyright>=1.1.381; extra == 'ci'
Requires-Dist: pytest-cov>=5.0.0; extra == 'ci'
Requires-Dist: pytest>=8.3.3; extra == 'ci'
Requires-Dist: ruff>=0.6.7; extra == 'ci'
Provides-Extra: debug
Requires-Dist: ipython>=8.18.1; extra == 'debug'
Provides-Extra: dev
Requires-Dist: ipython>=8.18.1; extra == 'dev'
Requires-Dist: pyhamcrest>=2.1.0; extra == 'dev'
Requires-Dist: pyright>=1.1.381; extra == 'dev'
Requires-Dist: pytest-cov>=5.0.0; extra == 'dev'
Requires-Dist: pytest>=8.3.3; extra == 'dev'
Requires-Dist: ruff>=0.6.7; extra == 'dev'
Provides-Extra: linting
Requires-Dist: ruff>=0.6.7; extra == 'linting'
Provides-Extra: nix
Requires-Dist: gitpython; extra == 'nix'
Requires-Dist: ipython>=8.18.1; extra == 'nix'
Requires-Dist: pyhamcrest>=2.1.0; extra == 'nix'
Requires-Dist: pyright>=1.1.381; extra == 'nix'
Requires-Dist: pytest-cov>=5.0.0; extra == 'nix'
Requires-Dist: pytest>=8.3.3; extra == 'nix'
Provides-Extra: release
Requires-Dist: python-semantic-release>=10.4.1; extra == 'release'
Provides-Extra: test
Requires-Dist: pyhamcrest>=2.1.0; extra == 'test'
Requires-Dist: pytest-cov>=5.0.0; extra == 'test'
Requires-Dist: pytest>=8.3.3; extra == 'test'
Provides-Extra: typing
Requires-Dist: pyright>=1.1.381; extra == 'typing'
